{
  "_id": "JQpXvDRGSKAm4iwI",
  "_key": "!items!JQpXvDRGSKAm4iwI",
  "name": "狐火弓",
  "folder": "VsvqWT2u088ca4pi",
  "sort": 188,
  "type": "weapon",
  "img": "https://raw.githubusercontent.com/game-icons/icons/master/delapouite/bow-arrow.svg",
  "system": {
    "description": "<p>能將放出的箭矢變為火焰的被EX背教者感染的弓。</p><p>使用該武器進行的攻擊可以以[種類：射擊]與《火舌》組合，此時該武器攻擊力+5。雙手持握。至近不可。</p><p><em>射程：30m</em> / <em>參照：IA P92</em></p>",
    "skillTmp": "melee",
    "skills": {},
    "saving": {
      "value": "",
      "difficulty": 0
    },
    "exp": 25,
    "equipment": true,
    "type": "射擊",
    "skill": "ranged",
    "add": -2,
    "attack": 9,
    "guard": 0,
    "range": "30m"
  },
  "effects": [],
  "flags": {
    "dx3rd-taiwan-zh-tw": {
      "category": "症候專用獨特道具 Syndrome Unique",
      "section": "關聯：戰神的軍師",
      "source": "IA P92"
    }
  },
  "ownership": {
    "default": 0
  }
}
