{
  "_id": "LFP6vKVxW5vleF55",
  "name": "絕影",
  "type": "effect",
  "img": "https://raw.githubusercontent.com/game-icons/icons/master/lorc/shadow-grasp.svg",
  "folder": "m920eVQK9xEhuLPi",
  "sort": 0,
  "system": {
    "description": "<p>瞬間多重投影出元型的虛像，讓幻影同時攻擊的異能。</p><p>前提條件：《雙重幻影》</p><p>與《雙重幻影》組合使用，組合的攻擊的判定達成值+[LV×5]。</p><p><em>參照：UAP21</em></p>",
    "skillTmp": "melee",
    "skills": {},
    "type": "normal",
    "skill": "syndrome",
    "difficulty": "對決",
    "limit": "極限",
    "timing": "major",
    "target": "-",
    "range": "武器",
    "roll": "-",
    "attackRoll": "-",
    "encroach": {
      "init": 2,
      "value": "2"
    },
    "level": {
      "init": 1,
      "max": 5,
      "upgrade": true
    },
    "exp": {
      "own": true,
      "upgrade": true
    },
    "effect": {
      "disable": "notCheck",
      "attributes": {}
    },
    "active": {
      "state": false,
      "disable": "battle"
    },
    "used": {
      "state": 0,
      "max": 0,
      "level": false,
      "disable": "notCheck"
    },
    "attributes": {},
    "getTarget": false,
    "macro": ""
  },
  "effects": [],
  "flags": {
    "dx3rd-taiwan-zh-tw": {
      "syndrome": "長青魔劍 Mistilteinn",
      "syndromeItemId": "prV8KorHRzKAVkva",
      "source": "UAP21"
    }
  },
  "ownership": {
    "default": 0
  },
  "_key": "!items!LFP6vKVxW5vleF55"
}
