{
  "_id": "FJPLnBuR8n3PP5Ol",
  "name": "融解",
  "type": "effect",
  "img": "https://raw.githubusercontent.com/game-icons/icons/master/lorc/frostfire.svg",
  "folder": "fTAZJwZUEo6ka7qa",
  "sort": 0,
  "system": {
    "description": "<p>于對象進行攻擊時宣言，該主要階段間，對象的攻擊的攻擊力-[LV×3]。</p><p><em>參照：EAP109</em></p>",
    "skillTmp": "melee",
    "skills": {},
    "type": "normal",
    "skill": "-",
    "difficulty": "自動成功",
    "limit": "1/回合",
    "timing": "auto",
    "target": "單體",
    "range": "至近",
    "roll": "-",
    "attackRoll": "-",
    "encroach": {
      "init": 2,
      "value": "2"
    },
    "level": {
      "init": 1,
      "max": 5,
      "upgrade": true
    },
    "exp": {
      "own": true,
      "upgrade": true
    },
    "effect": {
      "disable": "notCheck",
      "attributes": {}
    },
    "active": {
      "state": false,
      "disable": "battle"
    },
    "used": {
      "state": 0,
      "max": 1,
      "level": false,
      "disable": "round"
    },
    "attributes": {},
    "getTarget": false,
    "macro": ""
  },
  "effects": [],
  "flags": {
    "dx3rd-taiwan-zh-tw": {
      "syndrome": "冰炎奇蜥 Salamandra",
      "syndromeItemId": "QYuRS0HzX2yUU8d7",
      "source": "EAP109"
    }
  },
  "ownership": {
    "default": 0
  },
  "_key": "!items!FJPLnBuR8n3PP5Ol"
}
