{
  "_id": "hdkmpq0ijU0eW0Qo",
  "name": "雷之劍",
  "type": "effect",
  "img": "https://raw.githubusercontent.com/game-icons/icons/master/lorc/lightning-arc.svg",
  "folder": "MLSW5fEzXz5Degnd",
  "sort": 0,
  "system": {
    "description": "<p>將壓縮的電擊在至近距離炸裂開來的異能。</p><p>進行「攻擊力：+5」的射擊攻擊。</p><p>組合此異能的時候，可無視「不能以與你接戰的角色為對象」的異能效果。</p><p><em>參照：HRP77</em></p>",
    "skillTmp": "melee",
    "skills": {},
    "type": "normal",
    "skill": "rc",
    "difficulty": "對決",
    "limit": "LV/場景",
    "timing": "major",
    "target": "-",
    "range": "至近",
    "roll": "-",
    "attackRoll": "-",
    "encroach": {
      "init": 2,
      "value": ""
    },
    "level": {
      "init": 1,
      "max": 3,
      "upgrade": true
    },
    "exp": {
      "own": true,
      "upgrade": true
    },
    "effect": {
      "disable": "notCheck",
      "attributes": {}
    },
    "active": {
      "state": false,
      "disable": "-"
    },
    "used": {
      "state": 0,
      "max": 0,
      "level": true,
      "disable": "battle"
    },
    "attributes": {
      "attack": {
        "value": "5"
      }
    },
    "getTarget": false,
    "macro": ""
  },
  "effects": [],
  "flags": {
    "dx3rd-taiwan-zh-tw": {
      "syndrome": "雷擊黑犬 Black Dog",
      "syndromeItemId": "hWwcHd8Gt8C56UhO",
      "source": "HRP77"
    }
  },
  "ownership": {
    "default": 0
  },
  "_key": "!items!hdkmpq0ijU0eW0Qo"
}
