{
  "_id": "T09AJXWGVIfbYWLL",
  "name": "紅之宮殿 （紅の宮廷）",
  "type": "effect",
  "img": "https://raw.githubusercontent.com/game-icons/icons/master/delapouite/kraken-tentacle.svg",
  "folder": "JSUkgasOPh519Dvc",
  "sort": 0,
  "system": {
    "description": "<p>將對象招致存在于時空盡頭的阿撒托斯之鬥技場，強邀其進行決鬥的異能。</p><p>與對象以由你從<近戰><射擊><RC>之中選擇一項的技能進行對決，此次對決中無法使用異能。對在對決中失敗的一方（平手時則為雙方）造成[LV+7]D10點的HP傷害。</p><p><em>參照：NC P99</em></p>",
    "skillTmp": "melee",
    "skills": {},
    "type": "normal",
    "skill": "-",
    "difficulty": "參照效果",
    "limit": "鬥爭\n120% / 1/場景",
    "timing": "major",
    "target": "單體",
    "range": "視界",
    "roll": "-",
    "attackRoll": "-",
    "encroach": {
      "init": 5,
      "value": "5"
    },
    "level": {
      "init": 1,
      "max": 5,
      "upgrade": true
    },
    "exp": {
      "own": true,
      "upgrade": true
    },
    "effect": {
      "disable": "notCheck",
      "attributes": {}
    },
    "active": {
      "state": false,
      "disable": "battle"
    },
    "used": {
      "state": 0,
      "max": 1,
      "level": false,
      "disable": "battle"
    },
    "attributes": {},
    "getTarget": false,
    "macro": ""
  },
  "effects": [],
  "flags": {
    "dx3rd-taiwan-zh-tw": {
      "syndrome": "混沌原核 Azathoth",
      "syndromeItemId": "DNkvSNCxTwl41l1S",
      "source": "NC P99"
    }
  },
  "ownership": {
    "default": 0
  },
  "_key": "!items!T09AJXWGVIfbYWLL"
}
