{
  "_id": "PVlLLOpC8sDlDuxV",
  "name": "化學煙霧 (ケミカルスモッグ)",
  "type": "effect",
  "img": "https://raw.githubusercontent.com/game-icons/icons/master/caro-asercion/heraldic-sun.svg",
  "folder": "W4u8CenVorKafxlc",
  "sort": 0,
  "system": {
    "description": "<p>散佈遮蔽視線的物質，使周圍視野變差的異能。</p><p>通過這個異能，可以隱秘地行動。散佈的物質對人體沒有危害。GM覺得有必要的話，可以進行一個<RC>判定。</p><p><em>參照：BCP67</em></p>",
    "skillTmp": "melee",
    "skills": {},
    "type": "easy",
    "skill": "-",
    "difficulty": "自動成功",
    "limit": "-",
    "timing": "major",
    "target": "自身",
    "range": "至近",
    "roll": "-",
    "attackRoll": "-",
    "encroach": {
      "init": 0,
      "value": ""
    },
    "level": {
      "init": 1,
      "max": 1,
      "upgrade": true
    },
    "exp": {
      "own": true,
      "upgrade": true
    },
    "effect": {
      "disable": "notCheck",
      "attributes": {}
    },
    "active": {
      "state": false,
      "disable": "-"
    },
    "used": {
      "state": 0,
      "max": 0,
      "level": false,
      "disable": "notCheck"
    },
    "attributes": {},
    "getTarget": false,
    "macro": ""
  },
  "effects": [],
  "flags": {
    "dx3rd-taiwan-zh-tw": {
      "syndrome": "幻象惑星 Solaris",
      "syndromeItemId": "HgCooNxQHXJK0I8O",
      "source": "BCP67"
    }
  },
  "ownership": {
    "default": 0
  },
  "_key": "!items!PVlLLOpC8sDlDuxV"
}
