{
  "_id": "sTnTHsrLBcFqodlm",
  "name": "宿命之死",
  "type": "effect",
  "img": "https://raw.githubusercontent.com/game-icons/icons/master/lorc/cursed-star.svg",
  "folder": "nvsOMgfQh0V2uoKK",
  "sort": 0,
  "system": {
    "description": "<p>前提條件：《告死之鎖》</p><p>在對《告死之鎖》生效的對象進行傷害擲骰之前使用，傷害+[LV+3]D。</p><p><em>參照：UAP81</em></p>",
    "skillTmp": "melee",
    "skills": {},
    "type": "normal",
    "skill": "-",
    "difficulty": "自動成功",
    "limit": "極限 / 1/回合",
    "timing": "auto",
    "target": "單體",
    "range": "視界",
    "roll": "-",
    "attackRoll": "-",
    "encroach": {
      "init": 2,
      "value": ""
    },
    "level": {
      "init": 1,
      "max": 3,
      "upgrade": true
    },
    "exp": {
      "own": true,
      "upgrade": true
    },
    "effect": {
      "disable": "notCheck",
      "attributes": {}
    },
    "active": {
      "state": false,
      "disable": "-"
    },
    "used": {
      "state": 0,
      "max": 1,
      "level": false,
      "disable": "round"
    },
    "attributes": {},
    "getTarget": false,
    "macro": ""
  },
  "effects": [],
  "flags": {
    "dx3rd-taiwan-zh-tw": {
      "syndrome": "偽神天鎖 Gleipnir",
      "syndromeItemId": "wzWZsuLaBbQy6m0K",
      "source": "UAP81"
    }
  },
  "ownership": {
    "default": 0
  },
  "_key": "!items!sTnTHsrLBcFqodlm"
}
